<?xml version="1.0" encoding="UTF-8"?>
<beans xmlns="http://www.springframework.org/schema/beans"
       xmlns:xsi="http://www.w3.org/2001/XMLSchema-instance"
       xsi:schemaLocation="http://www.springframework.org/schema/beans
                           http://www.springframework.org/schema/beans/spring-beans-3.1.xsd">

    <!-- orchestra -->
    <!-- 1. initialization of all orchestra modules (required for core15 module) -->
    <import resource="classpath*:/META-INF/spring-orchestra-init.xml" />

    <!-- 2. the conversation scopes -->
    <bean class="org.springframework.beans.factory.config.CustomScopeConfigurer">
      <property name="scopes">
        <map>
          <entry key="conversation.manual">
            <bean class="org.apache.myfaces.orchestra.conversation.spring.SpringConversationScope">
              <property name="timeout" value="30" />
              <property name="advices">
                <list>
                  <!--<ref bean="persistentContextConversationInterceptor"/>-->
                </list>
              </property>
            </bean>
          </entry>

          <entry key="conversation.access">
            <bean class="org.apache.myfaces.orchestra.conversation.spring.SpringConversationScope">
              <property name="timeout" value="30" />
              <property name="advices">
                <list>
                  <!--<ref bean="persistentContextConversationInterceptor"/>-->
                </list>
              </property>
              <property name="lifetime" value="access"/>
            </bean>
          </entry>
        </map>
      </property>
    </bean>


    <!-- Trinidad dialog... -->
   <bean name="org.apache.myfaces.orchestra.conversation.AccessScopeManagerConfiguration"
         class="org.apache.myfaces.orchestra.conversation.AccessScopeManagerConfiguration"
         scope="singleton">

       <property name="ignoreViewIds">
           <set>
               <value>/__ADFv__.xhtml</value>
           </set>
       </property>
   </bean>


</beans>